{
  "courseId": "ch26",
  "lessons": [
    {
      "id": "ch26_01",
      "courseId": "ch26",
      "title": "java.timeパッケージの概要",
      "summary": "Java 8で導入されたjava.timeパッケージの基本クラスを学びます。LocalDate、LocalTime、LocalDateTimeの生成方法、イミュータブル（不変）な設計思想を理解します。",
      "estimatedMinutes": 6,
      "order": 1,
      "contents": [
        {
          "lessonId": "ch26_01",
          "sectionType": "overview",
          "title": "日付・時刻APIの概要",
          "body": "このレッスンでは以下を学びます:\n\n・java.timeパッケージの設計思想（不変・スレッドセーフ）\n・**LocalDate**, **LocalTime**, LocalDateTimeの違い\n・now(), of()による生成方法\n\n従来のDate/Calendarの問題を解決した新しいAPIです。",
          "code": null,
          "note": null,
          "order": 1
        },
        {
          "lessonId": "ch26_01",
          "sectionType": "rule",
          "title": "LocalDate・LocalTime・LocalDateTime",
          "body": "| クラス | 説明 |\n|---|---|\n| LocalDate | 年・月・日のみを表し、時刻情報を持ちません。ISO 8601形式（yyyy-MM-dd）で表現されます。 |\n| LocalTime | 時・分・秒・ナノ秒を表し、日付情報を持ちません。 |\n| LocalDateTime | 日付と時刻の両方を表します。 |\nいずれも**イミュータブル**であり、操作メソッドは新しいインスタンスを返します。\n元のオブジェクトは変更されないため、戻り値を受け取らないと変更は反映されません。\nコンストラクタはprivateなので、new LocalDate()のようなコードはコンパイルエラーになります。",
          "code": "import java.time.LocalDate;\nimport java.time.LocalTime;\nimport java.time.LocalDateTime;\n\n// 現在の日付・時刻\nLocalDate today = LocalDate.now();\nLocalTime now = LocalTime.now();\nLocalDateTime dateTime = LocalDateTime.now();\n\nSystem.out.println(today);    // 例: 2024-04-01\nSystem.out.println(now);      // 例: 14:30:15.123\nSystem.out.println(dateTime); // 例: 2024-04-01T14:30:15.123\n\n// イミュータブルの確認\nLocalDate d = LocalDate.of(2024, 1, 1);\nd.plusDays(10);  // 戻り値を受け取っていない！\nSystem.out.println(d); // 2024-01-01（変更されない）\n\nLocalDate d2 = d.plusDays(10); // 新しいインスタンスを受け取る\nSystem.out.println(d2); // 2024-01-11",
          "note": "操作メソッドの戻り値を受け取らないと変更が反映されない点は、試験で頻出のひっかけです。",
          "order": 2
        },
        {
          "lessonId": "ch26_01",
          "sectionType": "code",
          "title": "インスタンスの生成方法",
          "body": "now()メソッドは現在の日付・時刻を取得します。\nof()メソッドは指定した値でインスタンスを生成します。月はintまたはMonthEnum型で指定できます。\nparse()メソッドは文字列からインスタンスを生成します。\n不正な値を指定するとDateTimeExceptionがスローされます（例：月が13、日が32など）。\nLocalDateTimeはLocalDateとLocalTimeからも生成できます。",
          "code": "import java.time.*;\n\n// of()メソッド\nLocalDate d1 = LocalDate.of(2024, 3, 15);       // int指定\nLocalDate d2 = LocalDate.of(2024, Month.MARCH, 15); // Month enum\nLocalTime t1 = LocalTime.of(14, 30);             // 時, 分\nLocalTime t2 = LocalTime.of(14, 30, 45);         // 時, 分, 秒\nLocalDateTime dt1 = LocalDateTime.of(2024, 3, 15, 14, 30);\n\n// LocalDate + LocalTimeから生成\nLocalDateTime dt2 = LocalDateTime.of(d1, t1);\n\n// parse()メソッド\nLocalDate d3 = LocalDate.parse(\"2024-03-15\");\nLocalTime t3 = LocalTime.parse(\"14:30:45\");\nLocalDateTime dt3 = LocalDateTime.parse(\"2024-03-15T14:30:45\");\n\n// 不正な値 → DateTimeException\ntry {\n    LocalDate invalid = LocalDate.of(2024, 13, 1); // 月が13\n} catch (DateTimeException e) {\n    System.out.println(e.getMessage());\n}",
          "note": "コード中の「//」はコメント（説明文）です。プログラムの実行には影響しません。",
          "order": 3
        },
        {
          "lessonId": "ch26_01",
          "sectionType": "point",
          "title": "Monthとの関係とnewの禁止",
          "body": "月の指定にはint型（1〜12）またはMonth enum型が使えます。\nMonth.JANUARY = 1月、Month.DECEMBER = 12月で、0始まりではありません。\nこれは旧APIのCalendar.JANUARY = 0という直感に反する仕様が改善された点です。\nnew **LocalDate**()のような直接のコンストラクタ呼び出しはできず、コンパイルエラーになります。\nファクトリメソッドを使うことで、不正な状態のオブジェクト生成を防いでいます。",
          "code": "// Month enumの使用\nMonth m = Month.APRIL;\nSystem.out.println(m.getValue()); // 4\nSystem.out.println(m.name());     // APRIL\n\n// Month enumから日数を取得\nSystem.out.println(Month.FEBRUARY.length(false)); // 28（平年）\nSystem.out.println(Month.FEBRUARY.length(true));  // 29（閏年）\n\n// new は使えない\n// LocalDate d = new LocalDate(); // コンパイルエラー",
          "note": "旧APIのCalendarでは月が0始まり（0=1月）でしたが、java.timeでは1始まり（1=1月）です。",
          "order": 4
        },
        {
          "lessonId": "ch26_01",
          "sectionType": "tip",
          "title": "試験対策：日付・時刻の基本",
          "body": "Gold試験では、**イミュータブル**な操作の戻り値を受け取らないパターンが頻出です。\nnew演算子でのインスタンス生成がコンパイルエラーになることも覚えておきましょう。\nparse()に不正な形式の文字列を渡すとDateTimeParseExceptionが発生します。\nLocalDateにtime()メソッドは存在しません。時刻を扱うにはLocalTimeまたはLocalDateTimeを使います。\nLocalDateとLocalTimeの相互変換メソッドにも注意しましょう。",
          "code": null,
          "note": null,
          "order": 5
        }
      ],
      "quizzes": [
        {
          "id": "ch26_01_q1",
          "lessonId": "ch26_01",
          "type": "fourChoice",
          "question": "java.timeパッケージの日付・時刻クラスに関する説明として正しいものはどれですか？",
          "code": null,
          "explanation": "java.timeパッケージのLocalDate、LocalTime、LocalDateTimeはすべてイミュータブルです。操作メソッドは新しいインスタンスを返し、元のオブジェクトは変更されません。コンストラクタはprivateなのでnewで生成できません。",
          "choices": [
            {
              "id": "ch26_01_q1_a",
              "text": "すべてイミュータブルであり、操作メソッドは新しいインスタンスを返す",
              "isCorrect": true,
              "order": 1
            },
            {
              "id": "ch26_01_q1_b",
              "text": "ミュータブルであり、操作メソッドは自身を変更して返す",
              "isCorrect": false,
              "order": 2
            },
            {
              "id": "ch26_01_q1_c",
              "text": "new演算子でインスタンスを生成できる",
              "isCorrect": false,
              "order": 3
            },
            {
              "id": "ch26_01_q1_d",
              "text": "LocalDateはタイムゾーン情報を含む",
              "isCorrect": false,
              "order": 4
            }
          ],
          "correctOrder": null,
          "difficulty": "easy"
        },
        {
          "id": "ch26_01_q2",
          "lessonId": "ch26_01",
          "type": "outputPredict",
          "question": "次のコードの出力を予測してください。",
          "code": "import java.time.LocalDate;\npublic class Main {\n    public static void main(String[] args) {\n        LocalDate d = LocalDate.of(2024, 1, 31);\n        d.plusMonths(1);\n        System.out.println(d);\n    }\n}",
          "explanation": "LocalDateはイミュータブルなので、plusMonths(1)の戻り値を受け取らないと変更は反映されません。dは元の2024-01-31のままです。これはjava.time APIの重要な特徴であり、試験でも頻出のパターンです。",
          "choices": [
            {
              "id": "ch26_01_q2_a",
              "text": "2024-01-31",
              "isCorrect": true,
              "order": 1
            },
            {
              "id": "ch26_01_q2_b",
              "text": "2024-02-29",
              "isCorrect": false,
              "order": 2
            },
            {
              "id": "ch26_01_q2_c",
              "text": "2024-02-28",
              "isCorrect": false,
              "order": 3
            },
            {
              "id": "ch26_01_q2_d",
              "text": "コンパイルエラー",
              "isCorrect": false,
              "order": 4
            }
          ],
          "correctOrder": null,
          "difficulty": "normal"
        },
        {
          "id": "ch26_01_q3",
          "lessonId": "ch26_01",
          "type": "fillBlank",
          "question": "現在の日付を取得するには、LocalDate.___()メソッドを使う。",
          "code": null,
          "explanation": "LocalDate.now()は現在の日付を返すファクトリメソッドです。of()は指定した年月日でインスタンスを生成し、parse()は文字列からインスタンスを生成します。",
          "choices": [
            {
              "id": "ch26_01_q3_a",
              "text": "now",
              "isCorrect": true,
              "order": 1
            },
            {
              "id": "ch26_01_q3_b",
              "text": "today",
              "isCorrect": false,
              "order": 2
            },
            {
              "id": "ch26_01_q3_c",
              "text": "current",
              "isCorrect": false,
              "order": 3
            },
            {
              "id": "ch26_01_q3_d",
              "text": "getInstance",
              "isCorrect": false,
              "order": 4
            }
          ],
          "correctOrder": null,
          "difficulty": "hard"
        }
      ]
    },
    {
      "id": "ch26_02",
      "courseId": "ch26",
      "title": "日付・時刻の操作",
      "summary": "日付・時刻の加減算メソッド（plus/minus）、特定フィールドの変更メソッド（with）、期間を表すPeriodとDurationクラスの使い方を学びます。",
      "estimatedMinutes": 6,
      "order": 2,
      "contents": [
        {
          "lessonId": "ch26_02",
          "sectionType": "overview",
          "title": "日付・時刻の操作方法",
          "body": "このレッスンでは以下を学びます:\n\n・plus/minus系メソッドによる日付・時刻の加減算\n・with系メソッドによる特定フィールドの変更\n・Period（日付間隔）とDuration（時刻間隔）の使い分け\n\n不変オブジェクトの操作メソッドは新しいオブジェクトを返します。",
          "code": null,
          "note": null,
          "order": 1
        },
        {
          "lessonId": "ch26_02",
          "sectionType": "rule",
          "title": "plus/minusメソッド",
          "body": "| クラス | 主なメソッド |\n|---|---|\n| LocalDate | plusDays()、plusWeeks()、plusMonths()、plusYears() |\n| LocalTime | plusHours()、plusMinutes()、plusSeconds()、plusNanos() |\n| LocalDateTime | 上記すべてのメソッド |\n\n月末の日付に月を加算する場合、自動的に調整されます（例：1月31日 + 1ヶ月 = 2月28日or29日）。\nメソッドチェーンで複数の操作を連続して行えます。",
          "code": "import java.time.LocalDate;\nimport java.time.LocalTime;\nimport java.time.LocalDateTime;\n\nLocalDate d = LocalDate.of(2024, 3, 15);\nSystem.out.println(d.plusDays(10));    // 2024-03-25\nSystem.out.println(d.plusMonths(2));   // 2024-05-15\nSystem.out.println(d.minusYears(1));  // 2023-03-15\n\n// 月末の調整\nLocalDate jan31 = LocalDate.of(2024, 1, 31);\nSystem.out.println(jan31.plusMonths(1)); // 2024-02-29（閏年）\n\nLocalDate jan31b = LocalDate.of(2023, 1, 31);\nSystem.out.println(jan31b.plusMonths(1)); // 2023-02-28（平年）\n\n// メソッドチェーン\nLocalDate result = d.plusDays(5).plusMonths(1).minusYears(2);\nSystem.out.println(result); // 2022-04-20",
          "note": "月末の自動調整はGold試験で頻出です。1月31日に1ヶ月加算すると2月28日（or 29日）になります。",
          "order": 2
        },
        {
          "lessonId": "ch26_02",
          "sectionType": "code",
          "title": "withメソッドとTemporalAdjusters",
          "body": "with系メソッドは特定のフィールドを指定した値に変更した新しいインスタンスを返します。\nwithDayOfMonth()、withMonth()、withYear()などがあります。\n不正な値を指定するとDateTimeExceptionがスローされます。\nTemporalAdjustersクラスを使うと、「次の月曜日」や「月の最終日」などの複雑な調整が簡単に行えます。",
          "code": "import java.time.LocalDate;\nimport java.time.temporal.TemporalAdjusters;\nimport java.time.DayOfWeek;\n\nLocalDate d = LocalDate.of(2024, 3, 15);\n\n// withメソッド\nSystem.out.println(d.withDayOfMonth(1));  // 2024-03-01\nSystem.out.println(d.withMonth(6));       // 2024-06-15\nSystem.out.println(d.withYear(2025));     // 2025-03-15\n\n// TemporalAdjusters\nSystem.out.println(d.with(TemporalAdjusters.firstDayOfMonth()));  // 2024-03-01\nSystem.out.println(d.with(TemporalAdjusters.lastDayOfMonth()));   // 2024-03-31\nSystem.out.println(d.with(TemporalAdjusters.next(DayOfWeek.MONDAY))); // 次の月曜\nSystem.out.println(d.with(TemporalAdjusters.firstDayOfNextMonth())); // 2024-04-01",
          "note": "コード中の「//」はコメント（説明文）です。プログラムの実行には影響しません。",
          "order": 3
        },
        {
          "lessonId": "ch26_02",
          "sectionType": "point",
          "title": "PeriodとDuration",
          "body": "Periodは年・月・日単位の期間を表し、LocalDateと共に使用します。\nDurationは時・分・秒・ナノ秒単位の期間を表し、LocalTimeやLocalDateTimeと共に使用します。\nPeriod.between()で2つの日付間の期間を計算できます。\nDuration.between()で2つの時刻間の期間を計算できます。\nPeriodをLocalTimeに、DurationをLocalDateに適用するとUnsupportedTemporalTypeExceptionが発生します。",
          "code": "import java.time.*;\n\n// Period（年月日の期間）\nPeriod p1 = Period.of(1, 2, 3);  // 1年2ヶ月3日\nPeriod p2 = Period.ofMonths(6);   // 6ヶ月\nPeriod p3 = Period.between(\n    LocalDate.of(2024, 1, 1),\n    LocalDate.of(2024, 4, 15)\n); // 3ヶ月14日\n\nLocalDate d = LocalDate.of(2024, 1, 1);\nSystem.out.println(d.plus(p1)); // 2025-03-04\n\n// Duration（時間の期間）\nDuration d1 = Duration.ofHours(5);    // 5時間\nDuration d2 = Duration.ofMinutes(90); // 90分\nDuration d3 = Duration.between(\n    LocalTime.of(10, 0),\n    LocalTime.of(14, 30)\n); // 4時間30分\n\nLocalTime t = LocalTime.of(10, 0);\nSystem.out.println(t.plus(d1)); // 15:00\n\n// 型の不一致 → 例外\n// LocalTime.now().plus(p1); // UnsupportedTemporalTypeException",
          "note": "PeriodはLocalDateに、DurationはLocalTimeに使うことを覚えましょう。混同は試験で問われます。",
          "order": 4
        },
        {
          "lessonId": "ch26_02",
          "sectionType": "tip",
          "title": "試験対策：日付操作",
          "body": "月末の自動調整（1月31日 + 1ヶ月 = 2月28日/29日）は必ず出題されます。\nPeriodとDurationの使い分け（日付にはPeriod、時刻にはDuration）を覚えましょう。\nChronoUnit.DAYS.between()で2つの日付間の日数を計算できることも覚えておきましょう。\nPeriodのtoTotalMonths()メソッドで合計月数を取得できます。\nDurationのtoHours()、toMinutes()メソッドで単位変換ができます。",
          "code": null,
          "note": null,
          "order": 5
        }
      ],
      "quizzes": [
        {
          "id": "ch26_02_q1",
          "lessonId": "ch26_02",
          "type": "outputPredict",
          "question": "次のコードの出力を予測してください。",
          "code": "import java.time.LocalDate;\npublic class Main {\n    public static void main(String[] args) {\n        LocalDate d = LocalDate.of(2024, 1, 31);\n        d = d.plusMonths(1);\n        System.out.println(d);\n    }\n}",
          "explanation": "2024年は閏年なので2月は29日まであります。1月31日に1ヶ月加算すると、31日は2月に存在しないため自動的に2月の最終日（29日）に調整されます。戻り値をdに代入しているので変更が反映されます。",
          "choices": [
            {
              "id": "ch26_02_q1_a",
              "text": "2024-02-29",
              "isCorrect": true,
              "order": 1
            },
            {
              "id": "ch26_02_q1_b",
              "text": "2024-02-28",
              "isCorrect": false,
              "order": 2
            },
            {
              "id": "ch26_02_q1_c",
              "text": "2024-01-31",
              "isCorrect": false,
              "order": 3
            },
            {
              "id": "ch26_02_q1_d",
              "text": "DateTimeException",
              "isCorrect": false,
              "order": 4
            }
          ],
          "correctOrder": null,
          "difficulty": "easy"
        },
        {
          "id": "ch26_02_q2",
          "lessonId": "ch26_02",
          "type": "fourChoice",
          "question": "PeriodとDurationの説明として正しいものはどれですか？",
          "code": null,
          "explanation": "Periodは年・月・日の期間を表し、LocalDateと共に使用します。DurationはLocalTimeやInstantなどの時間ベースのオブジェクトと共に使用します。PeriodをLocalTimeに適用するとUnsupportedTemporalTypeExceptionが発生します。",
          "choices": [
            {
              "id": "ch26_02_q2_a",
              "text": "PeriodはLocalDateに、DurationはLocalTimeに使用する",
              "isCorrect": true,
              "order": 1
            },
            {
              "id": "ch26_02_q2_b",
              "text": "PeriodはLocalTimeに、DurationはLocalDateに使用する",
              "isCorrect": false,
              "order": 2
            },
            {
              "id": "ch26_02_q2_c",
              "text": "PeriodとDurationはどちらもLocalDateに使用できる",
              "isCorrect": false,
              "order": 3
            },
            {
              "id": "ch26_02_q2_d",
              "text": "PeriodとDurationは同じクラスのエイリアスである",
              "isCorrect": false,
              "order": 4
            }
          ],
          "correctOrder": null,
          "difficulty": "normal"
        },
        {
          "id": "ch26_02_q3",
          "lessonId": "ch26_02",
          "type": "outputPredict",
          "question": "次のコードの出力を予測してください。",
          "code": "import java.time.LocalDate;\nimport java.time.Period;\npublic class Main {\n    public static void main(String[] args) {\n        LocalDate d1 = LocalDate.of(2024, 1, 1);\n        LocalDate d2 = LocalDate.of(2024, 3, 15);\n        Period p = Period.between(d1, d2);\n        System.out.println(p.getMonths() + \" months \" + p.getDays() + \" days\");\n    }\n}",
          "explanation": "Period.between()は2つの日付間の期間を計算します。2024-01-01から2024-03-15は2ヶ月14日です。getMonths()は2を返し、getDays()は14を返します。",
          "choices": [
            {
              "id": "ch26_02_q3_a",
              "text": "2 months 14 days",
              "isCorrect": true,
              "order": 1
            },
            {
              "id": "ch26_02_q3_b",
              "text": "2 months 15 days",
              "isCorrect": false,
              "order": 2
            },
            {
              "id": "ch26_02_q3_c",
              "text": "3 months 14 days",
              "isCorrect": false,
              "order": 3
            },
            {
              "id": "ch26_02_q3_d",
              "text": "74 months 0 days",
              "isCorrect": false,
              "order": 4
            }
          ],
          "correctOrder": null,
          "difficulty": "hard"
        },
        {
          "id": "ch26_02_q4",
          "lessonId": "ch26_02",
          "type": "codeComplete",
          "question": "LocalDateを使って日付を操作するコードを完成させてください。",
          "code": null,
          "explanation": "LocalDate.now()で現在日付を取得し、plusDays()で日数を加算します。不変オブジェクトなので新しいインスタンスが返ります。",
          "choices": [],
          "correctOrder": null,
          "executionResult": null,
          "fixedExecutionResult": null,
          "codeTemplate": "LocalDate today = LocalDate.__BLANK_1__();\nLocalDate nextWeek = today.__BLANK_2__(7);",
          "blanks": [
            {
              "id": "blank_1",
              "label": "①現在日付",
              "choices": [
                {
                  "id": "b1_c1",
                  "text": "now",
                  "isCorrect": true
                },
                {
                  "id": "b1_c2",
                  "text": "today",
                  "isCorrect": false
                },
                {
                  "id": "b1_c3",
                  "text": "current",
                  "isCorrect": false
                }
              ]
            },
            {
              "id": "blank_2",
              "label": "②日数加算",
              "choices": [
                {
                  "id": "b2_c1",
                  "text": "plusDays",
                  "isCorrect": true
                },
                {
                  "id": "b2_c2",
                  "text": "addDays",
                  "isCorrect": false
                },
                {
                  "id": "b2_c3",
                  "text": "plus",
                  "isCorrect": false
                }
              ]
            }
          ],
          "combinedResults": null,
          "requiredSelections": null,
          "certificationTopic": null,
          "difficulty": "easy"
        }
      ]
    },
    {
      "id": "ch26_03",
      "courseId": "ch26",
      "title": "DateTimeFormatter",
      "summary": "日付・時刻のフォーマットとパースを学びます。定義済みフォーマッター、カスタムパターンの指定方法、format()とparse()メソッドの使い方を理解します。",
      "estimatedMinutes": 6,
      "order": 3,
      "contents": [
        {
          "lessonId": "ch26_03",
          "sectionType": "overview",
          "title": "DateTimeFormatterとは",
          "body": "このレッスンでは以下を学びます:\n\n・DateTimeFormatterの事前定義フォーマッタ\n・ofPattern()でカスタムフォーマットを作成\n・parse()で文字列から日時オブジェクトに変換\n\n日時と文字列の相互変換は実務で頻繁に使います。",
          "code": null,
          "note": null,
          "order": 1
        },
        {
          "lessonId": "ch26_03",
          "sectionType": "rule",
          "title": "定義済みフォーマッター",
          "body": "DateTimeFormatterにはISO標準の定義済みフォーマッターが用意されています。\nISO_LOCAL_DATE：yyyy-MM-dd形式（例：2024-03-15）\nISO_LOCAL_TIME：HH:mm:ss形式（例：14:30:45）\nISO_LOCAL_DATE_TIME：yyyy-MM-ddTHH:mm:ss形式（例：2024-03-15T14:30:45）\nこれらはLocalDate、LocalTimeなどのtoString()と同じ形式です。\nFormatStyleを使ったofLocalizedDate()でロケール対応のフォーマットも可能です。",
          "code": "import java.time.LocalDate;\nimport java.time.LocalDateTime;\nimport java.time.format.DateTimeFormatter;\nimport java.time.format.FormatStyle;\nimport java.util.Locale;\n\nLocalDate d = LocalDate.of(2024, 3, 15);\n\n// 定義済みフォーマッター\nString s1 = d.format(DateTimeFormatter.ISO_LOCAL_DATE);\nSystem.out.println(s1); // 2024-03-15\n\nLocalDateTime dt = LocalDateTime.of(2024, 3, 15, 14, 30);\nString s2 = dt.format(DateTimeFormatter.ISO_LOCAL_DATE_TIME);\nSystem.out.println(s2); // 2024-03-15T14:30:00\n\n// ロケール対応フォーマット\nDateTimeFormatter jf = DateTimeFormatter\n    .ofLocalizedDate(FormatStyle.FULL)\n    .withLocale(Locale.JAPAN);\nSystem.out.println(d.format(jf)); // 2024年3月15日金曜日",
          "note": "ISO_LOCAL_DATE_TIMEは日付と時刻をTで区切る形式です。",
          "order": 2
        },
        {
          "lessonId": "ch26_03",
          "sectionType": "code",
          "title": "カスタムパターン（ofPattern）",
          "body": "**DateTimeFormatter**.ofPattern()でカスタムフォーマットパターンを指定できます。\n主なパターン文字：y（年）、M（月）、d（日）、H（時24h）、h（時12h）、m（分）、s（秒）\n大文字と小文字の違いに注意してください（Mは月、mは分、Hは24時間制、hは12時間制）。\nパターン文字の繰り返し回数で出力の桁数が決まります（yyは2桁年、yyyyは4桁年）。\nシングルクォートで囲んだ文字はリテラルとして出力されます。",
          "code": "import java.time.LocalDateTime;\nimport java.time.format.DateTimeFormatter;\n\nLocalDateTime dt = LocalDateTime.of(2024, 3, 15, 14, 30, 45);\n\n// カスタムパターン\nDateTimeFormatter f1 = DateTimeFormatter.ofPattern(\"yyyy/MM/dd\");\nSystem.out.println(dt.format(f1)); // 2024/03/15\n\nDateTimeFormatter f2 = DateTimeFormatter.ofPattern(\"yyyy年MM月dd日 HH時mm分\");\nSystem.out.println(dt.format(f2)); // 2024年03月15日 14時30分\n\nDateTimeFormatter f3 = DateTimeFormatter.ofPattern(\"MM-dd-yyyy\");\nSystem.out.println(dt.format(f3)); // 03-15-2024\n\n// 注意：LocalDateに時刻パターンを使うとエラー\nLocalDate d = LocalDate.of(2024, 3, 15);\nDateTimeFormatter f4 = DateTimeFormatter.ofPattern(\"yyyy/MM/dd HH:mm\");\n// d.format(f4); // UnsupportedTemporalTypeException",
          "note": "コード中の「//」はコメント（説明文）です。プログラムの実行には影響しません。",
          "order": 3
        },
        {
          "lessonId": "ch26_03",
          "sectionType": "point",
          "title": "parse()メソッドの使い方",
          "body": "parse()メソッドで文字列から日付・時刻オブジェクトを生成できます。\n**LocalDate**.parse(文字列, フォーマッター)の形式で使います。\nフォーマッターを省略すると、ISO標準形式（yyyy-MM-dd等）でパースします。\nパターンに一致しない文字列を渡すとDateTimeParseExceptionがスローされます。\nフォーマッターのパターンと文字列のフォーマットは完全に一致する必要があります。",
          "code": "import java.time.LocalDate;\nimport java.time.LocalDateTime;\nimport java.time.format.DateTimeFormatter;\n\n// デフォルト形式でパース\nLocalDate d1 = LocalDate.parse(\"2024-03-15\");\nSystem.out.println(d1); // 2024-03-15\n\n// カスタムパターンでパース\nDateTimeFormatter f = DateTimeFormatter.ofPattern(\"yyyy/MM/dd\");\nLocalDate d2 = LocalDate.parse(\"2024/03/15\", f);\nSystem.out.println(d2); // 2024-03-15\n\n// パースエラー\ntry {\n    LocalDate.parse(\"2024/03/15\"); // ISO形式でないためエラー\n} catch (Exception e) {\n    System.out.println(\"DateTimeParseException\");\n}\n\n// LocalDateTimeのパース\nDateTimeFormatter dtf = DateTimeFormatter.ofPattern(\"yyyy/MM/dd HH:mm\");\nLocalDateTime dt = LocalDateTime.parse(\"2024/03/15 14:30\", dtf);\nSystem.out.println(dt); // 2024-03-15T14:30",
          "note": "parse()とformat()は逆の操作です。同じフォーマッターでformat→parseを往復できます。",
          "order": 4
        },
        {
          "lessonId": "ch26_03",
          "sectionType": "tip",
          "title": "試験対策：フォーマットとパース",
          "body": "Gold試験では、ofPattern()のパターン文字の意味を正確に理解しているかが問われます。\nMとmの違い（M=月、m=分）、Hとhの違い（H=24時間制、h=12時間制）は必須です。\nLocalDateに時刻のパターンを使うとUnsupportedTemporalTypeExceptionが発生します。\nパース時にフォーマットが一致しないとDateTimeParseExceptionが発生します。\nformat()はフォーマッターとオブジェクトの両方から呼べます（dt.format(f) と f.format(dt)は同じ結果）。",
          "code": null,
          "note": null,
          "order": 5
        }
      ],
      "quizzes": [
        {
          "id": "ch26_03_q1",
          "lessonId": "ch26_03",
          "type": "outputPredict",
          "question": "次のコードの出力を予測してください。",
          "code": "import java.time.LocalDateTime;\nimport java.time.format.DateTimeFormatter;\npublic class Main {\n    public static void main(String[] args) {\n        LocalDateTime dt = LocalDateTime.of(2024, 3, 5, 9, 7);\n        DateTimeFormatter f = DateTimeFormatter.ofPattern(\"yyyy/MM/dd HH:mm\");\n        System.out.println(dt.format(f));\n    }\n}",
          "explanation": "ofPattern(\"yyyy/MM/dd HH:mm\")で指定したパターンにより、年は4桁、月と日は2桁（ゼロ埋め）、24時間制の時と分も2桁で表示されます。3月は03、5日は05、9時は09、7分は07と表示されます。",
          "choices": [
            {
              "id": "ch26_03_q1_a",
              "text": "2024/03/05 09:07",
              "isCorrect": true,
              "order": 1
            },
            {
              "id": "ch26_03_q1_b",
              "text": "2024/3/5 9:7",
              "isCorrect": false,
              "order": 2
            },
            {
              "id": "ch26_03_q1_c",
              "text": "2024-03-05T09:07",
              "isCorrect": false,
              "order": 3
            },
            {
              "id": "ch26_03_q1_d",
              "text": "DateTimeParseException",
              "isCorrect": false,
              "order": 4
            }
          ],
          "correctOrder": null,
          "difficulty": "easy"
        },
        {
          "id": "ch26_03_q2",
          "lessonId": "ch26_03",
          "type": "fillBlank",
          "question": "DateTimeFormatterでカスタムパターンを指定するには、DateTimeFormatter.___()メソッドを使う。",
          "code": null,
          "explanation": "DateTimeFormatter.ofPattern()メソッドにパターン文字列を渡すことで、カスタムフォーマッターを作成できます。パターン文字には y（年）、M（月）、d（日）、H（時）、m（分）、s（秒）などがあります。",
          "choices": [
            {
              "id": "ch26_03_q2_a",
              "text": "ofPattern",
              "isCorrect": true,
              "order": 1
            },
            {
              "id": "ch26_03_q2_b",
              "text": "format",
              "isCorrect": false,
              "order": 2
            },
            {
              "id": "ch26_03_q2_c",
              "text": "newPattern",
              "isCorrect": false,
              "order": 3
            },
            {
              "id": "ch26_03_q2_d",
              "text": "createFormat",
              "isCorrect": false,
              "order": 4
            }
          ],
          "correctOrder": null,
          "difficulty": "normal"
        },
        {
          "id": "ch26_03_q3",
          "lessonId": "ch26_03",
          "type": "fourChoice",
          "question": "DateTimeFormatterのパターン文字について正しい組み合わせはどれですか？",
          "code": null,
          "explanation": "M（大文字）は月（Month）を表し、m（小文字）は分（minute）を表します。H（大文字）は24時間制の時（Hour）を表し、h（小文字）は12時間制の時を表します。この大文字小文字の違いは試験で頻出です。",
          "choices": [
            {
              "id": "ch26_03_q3_a",
              "text": "M=月、m=分、H=24時間制の時、h=12時間制の時",
              "isCorrect": true,
              "order": 1
            },
            {
              "id": "ch26_03_q3_b",
              "text": "M=分、m=月、H=12時間制の時、h=24時間制の時",
              "isCorrect": false,
              "order": 2
            },
            {
              "id": "ch26_03_q3_c",
              "text": "M=月、m=分、H=12時間制の時、h=24時間制の時",
              "isCorrect": false,
              "order": 3
            },
            {
              "id": "ch26_03_q3_d",
              "text": "M=分、m=月、H=24時間制の時、h=12時間制の時",
              "isCorrect": false,
              "order": 4
            }
          ],
          "correctOrder": null,
          "difficulty": "hard"
        },
        {
          "id": "ch26_03_q4",
          "lessonId": "ch26_03",
          "type": "multiChoice",
          "question": "java.timeパッケージのクラスをすべて選んでください。",
          "code": null,
          "explanation": "LocalDate, LocalTime, Duration, Periodはjava.timeのクラスです。Calendarはjava.utilのレガシーAPIです。",
          "choices": [
            {
              "id": "c1",
              "text": "LocalDate",
              "isCorrect": true,
              "order": 1
            },
            {
              "id": "c2",
              "text": "LocalTime",
              "isCorrect": true,
              "order": 2
            },
            {
              "id": "c3",
              "text": "Duration",
              "isCorrect": true,
              "order": 3
            },
            {
              "id": "c4",
              "text": "Calendar",
              "isCorrect": false,
              "order": 4
            },
            {
              "id": "c5",
              "text": "Period",
              "isCorrect": true,
              "order": 5
            }
          ],
          "correctOrder": null,
          "executionResult": null,
          "fixedExecutionResult": null,
          "codeTemplate": null,
          "blanks": null,
          "combinedResults": null,
          "requiredSelections": 4,
          "certificationTopic": null,
          "difficulty": "normal"
        }
      ]
    },
    {
      "id": "ch26_04",
      "courseId": "ch26",
      "title": "ZonedDateTimeとInstant",
      "summary": "タイムゾーンを扱うZonedDateTimeクラスと、エポックベースの時点を表すInstantクラスを学びます。ZoneIdの使い方、型間の変換方法を理解します。",
      "estimatedMinutes": 6,
      "order": 4,
      "contents": [
        {
          "lessonId": "ch26_04",
          "sectionType": "overview",
          "title": "タイムゾーンとInstant",
          "body": "このレッスンでは以下を学びます:\n\n・ZonedDateTimeでタイムゾーン付き日時を扱う\n・Instantでエポック秒から日時を生成\n・各クラス間の変換方法\n\nグローバルなアプリケーションで必須の知識です。",
          "code": null,
          "note": null,
          "order": 1
        },
        {
          "lessonId": "ch26_04",
          "sectionType": "rule",
          "title": "ZoneIdとZonedDateTime",
          "body": "ZoneIdはタイムゾーンを表すクラスで、ZoneId.of(\"Asia/Tokyo\")のように生成します。\nZonedDateTimeはLocalDateTimeにZoneIdを加えたものです。\n**ZonedDateTime**.now()で現在のタイムゾーン付き日時を取得できます。\nLocalDateTimeとZoneIdからZonedDateTimeを生成できます（atZone()メソッド）。\nZonedDateTimeのtoString()にはタイムゾーン情報（オフセットとゾーンID）が含まれます。\nZoneId.getAvailableZoneIds()で利用可能なタイムゾーンIDの一覧を取得できます。",
          "code": "import java.time.*;\n\n// ZoneIdの取得\nZoneId tokyo = ZoneId.of(\"Asia/Tokyo\");\nZoneId utc = ZoneId.of(\"UTC\");\nZoneId ny = ZoneId.of(\"America/New_York\");\n\n// ZonedDateTimeの生成\nZonedDateTime zdt1 = ZonedDateTime.now(tokyo);\nSystem.out.println(zdt1); // 例: 2024-03-15T14:30:00+09:00[Asia/Tokyo]\n\n// LocalDateTimeからZonedDateTimeへ\nLocalDateTime ldt = LocalDateTime.of(2024, 3, 15, 14, 30);\nZonedDateTime zdt2 = ldt.atZone(tokyo);\nSystem.out.println(zdt2); // 2024-03-15T14:30+09:00[Asia/Tokyo]\n\n// タイムゾーンの変換\nZonedDateTime zdtNY = zdt2.withZoneSameInstant(ny);\nSystem.out.println(zdtNY); // 2024-03-15T01:30-04:00[America/New_York]",
          "note": "withZoneSameInstant()は同じ瞬間を別のタイムゾーンで表現します。withZoneSameLocal()はローカル時刻を維持してゾーンだけ変更します。",
          "order": 2
        },
        {
          "lessonId": "ch26_04",
          "sectionType": "code",
          "title": "Instantクラス",
          "body": "Instantはエポック（1970-01-01T00:00:00Z）からの経過時間で時点を表します。\nInstant.now()で現在の瞬間を取得し、Instant.ofEpochSecond()でエポック秒から生成します。\nInstantはタイムゾーンの概念を持たず、常にUTCベースです。\nInstantとZonedDateTimeは相互変換できます。\nDuration.between()でInstant間の時間差を計算できます。",
          "code": "import java.time.*;\n\n// Instantの生成\nInstant now = Instant.now();\nSystem.out.println(now); // 例: 2024-03-15T05:30:00.123Z\n\n// エポック秒から生成\nInstant epoch = Instant.ofEpochSecond(0);\nSystem.out.println(epoch); // 1970-01-01T00:00:00Z\n\nInstant i = Instant.ofEpochSecond(1000000);\nSystem.out.println(i); // 1970-01-12T13:46:40Z\n\n// ZonedDateTimeとの変換\nZonedDateTime zdt = now.atZone(ZoneId.of(\"Asia/Tokyo\"));\nSystem.out.println(zdt); // UTC+9で表示\n\nInstant fromZdt = zdt.toInstant();\nSystem.out.println(fromZdt.equals(now)); // true\n\n// Instant間の期間\nInstant i1 = Instant.parse(\"2024-01-01T00:00:00Z\");\nInstant i2 = Instant.parse(\"2024-01-02T12:00:00Z\");\nDuration d = Duration.between(i1, i2);\nSystem.out.println(d.toHours()); // 36",
          "note": "コード中の「//」はコメント（説明文）です。プログラムの実行には影響しません。",
          "order": 3
        },
        {
          "lessonId": "ch26_04",
          "sectionType": "point",
          "title": "型間の変換まとめ",
          "body": "| 変換 | 方法 |\n|---|---|\n| LocalDateTime → ZonedDateTime | atZone(ZoneId)を使用します。 |\n| ZonedDateTime → LocalDateTime | toLocalDateTime()を使用します。 |\n| ZonedDateTime → Instant | toInstant()を使用します。 |\n| LocalDateTime → Instant | 直接変換はできず、一度ZonedDateTimeを経由する必要があります。 |\nこれらの変換関係はGold試験で頻出です。",
          "code": "import java.time.*;\n\nZoneId tokyo = ZoneId.of(\"Asia/Tokyo\");\n\n// LocalDateTime → ZonedDateTime\nLocalDateTime ldt = LocalDateTime.of(2024, 3, 15, 14, 30);\nZonedDateTime zdt = ldt.atZone(tokyo);\n\n// ZonedDateTime → LocalDateTime\nLocalDateTime ldt2 = zdt.toLocalDateTime();\n\n// ZonedDateTime → LocalDate / LocalTime\nLocalDate ld = zdt.toLocalDate();\nLocalTime lt = zdt.toLocalTime();\n\n// ZonedDateTime → Instant\nInstant inst = zdt.toInstant();\n\n// Instant → ZonedDateTime\nZonedDateTime zdt2 = inst.atZone(tokyo);\n\n// LocalDateTime → Instant（ZonedDateTime経由）\nInstant inst2 = ldt.atZone(tokyo).toInstant();",
          "note": "LocalDateTimeからInstantへの直接変換はできない点に注意しましょう。",
          "order": 4
        },
        {
          "lessonId": "ch26_04",
          "sectionType": "tip",
          "title": "試験対策：ZonedDateTimeとInstant",
          "body": "・Gold試験ではwithZoneSameInstant()とwithZoneSameLocal()の違いが問われます。\n・withZoneSameInstant()は同じ瞬間を別ゾーンで表現（時刻が変わる）、withZoneSameLocal()はローカル時刻を維持してゾーンだけ変更（瞬間が変わる）です。\n・InstantにはplusDays()等のメソッドがなく、plus(Duration)で操作することに注意しましょう。\n\n型変換の経路を図で整理しておくと理解が深まります。\nZoneId.of()に不正なゾーンIDを渡すとZoneRulesExceptionが発生します。",
          "code": null,
          "note": null,
          "order": 5
        }
      ],
      "quizzes": [
        {
          "id": "ch26_04_q1",
          "lessonId": "ch26_04",
          "type": "fourChoice",
          "question": "Instantに関する説明として正しいものはどれですか？",
          "code": null,
          "explanation": "Instantはエポック（1970-01-01T00:00:00Z）からの経過時間で時点を表し、常にUTCベースです。タイムゾーンの概念を持たず、特定の瞬間を一意に特定します。atZone()でZonedDateTimeに変換できます。",
          "choices": [
            {
              "id": "ch26_04_q1_a",
              "text": "1970年1月1日UTCからの経過時間で時点を表す",
              "isCorrect": true,
              "order": 1
            },
            {
              "id": "ch26_04_q1_b",
              "text": "タイムゾーン情報を内部に保持している",
              "isCorrect": false,
              "order": 2
            },
            {
              "id": "ch26_04_q1_c",
              "text": "LocalDateTimeのサブクラスである",
              "isCorrect": false,
              "order": 3
            },
            {
              "id": "ch26_04_q1_d",
              "text": "plusDays()メソッドで日数を加算できる",
              "isCorrect": false,
              "order": 4
            }
          ],
          "correctOrder": null,
          "difficulty": "easy"
        },
        {
          "id": "ch26_04_q2",
          "lessonId": "ch26_04",
          "type": "outputPredict",
          "question": "次のコードの出力を予測してください。",
          "code": "import java.time.*;\npublic class Main {\n    public static void main(String[] args) {\n        LocalDateTime ldt = LocalDateTime.of(2024, 3, 15, 12, 0);\n        ZonedDateTime zdt = ldt.atZone(ZoneId.of(\"Asia/Tokyo\"));\n        Instant inst = zdt.toInstant();\n        System.out.println(inst);\n    }\n}",
          "explanation": "東京（UTC+9）の2024-03-15T12:00をUTCに変換すると、9時間引かれて2024-03-15T03:00:00Zになります。InstantのtoString()はUTC時刻にZを付けて表示します。",
          "choices": [
            {
              "id": "ch26_04_q2_a",
              "text": "2024-03-15T03:00:00Z",
              "isCorrect": true,
              "order": 1
            },
            {
              "id": "ch26_04_q2_b",
              "text": "2024-03-15T12:00:00Z",
              "isCorrect": false,
              "order": 2
            },
            {
              "id": "ch26_04_q2_c",
              "text": "2024-03-15T21:00:00Z",
              "isCorrect": false,
              "order": 3
            },
            {
              "id": "ch26_04_q2_d",
              "text": "2024-03-15T12:00:00+09:00",
              "isCorrect": false,
              "order": 4
            }
          ],
          "correctOrder": null,
          "difficulty": "normal"
        },
        {
          "id": "ch26_04_q3",
          "lessonId": "ch26_04",
          "type": "errorFind",
          "question": "次のコードに含まれるエラーを選んでください。",
          "code": "import java.time.*;\npublic class Main {\n    public static void main(String[] args) {\n        LocalDateTime ldt = LocalDateTime.of(2024, 3, 15, 14, 30);\n        Instant inst = ldt.toInstant();\n        System.out.println(inst);\n    }\n}",
          "explanation": "LocalDateTimeからInstantへの直接変換はできません。LocalDateTimeにはパラメータなしのtoInstant()メソッドがありません（タイムゾーン情報がないためUTC時刻を特定できない）。toInstant(ZoneOffset)は存在しますが、引数なしでは呼べずコンパイルエラーとなります。atZone()でZonedDateTimeに変換してからtoInstant()を呼ぶのが正しい方法です。",
          "choices": [
            {
              "id": "ch26_04_q3_a",
              "text": "LocalDateTimeにパラメータなしのtoInstant()メソッドは存在しない",
              "isCorrect": true,
              "order": 1
            },
            {
              "id": "ch26_04_q3_b",
              "text": "LocalDateTime.of()の引数の数が間違っている",
              "isCorrect": false,
              "order": 2
            },
            {
              "id": "ch26_04_q3_c",
              "text": "Instant型の変数にLocalDateTimeの値を代入できない",
              "isCorrect": false,
              "order": 3
            },
            {
              "id": "ch26_04_q3_d",
              "text": "System.out.println()でInstantを出力できない",
              "isCorrect": false,
              "order": 4
            }
          ],
          "correctOrder": null,
          "difficulty": "hard"
        }
      ]
    }
  ]
}